[
  {
    "url": "https://www.gov.cn/zhengce/content/202312/content_6923076.htm",
    "title": "中国政府网_中央人民政府门户网站",
    "content": "![](https://www.gov.cn/)\n\nhttps://www.gov.cn/\n\n## [全国政协十四届四次会议闭幕会举行 习近平等党和国家领导人出席](https://www.gov.cn/zhuanti/2026qglhzb/live/20260311a596378.html)\n\n[闭幕会通过了政协常委会工作报告决议](https://www.gov.cn/zhuanti/2026nztj/2026qglh/yw/202603/content_7061977.htm) \\| [通过了提案工作情况报告决议](https://www.gov.cn/zhuanti/2026nztj/2026qglh/yw/202603/content_7061978.htm) \\| [通过了提案审查情况报告](https://www.gov.cn/zhuanti/2026nztj/2026qglh/yw/202603/content_7061979.htm) \\| [通过了政协第十四届全国委员会第四次会议政治决议](https://www.gov.cn/zhuanti/2026nztj/2026qglh/yw/202603/content_7061980.htm)\n\n## [全国政协十四届四次会议闭幕会举行 习近平等党和国家领导人出席](https://www.gov.cn/zhuanti/2026qglhzb/live/20260311a596378.html)\n\n[闭幕会通过了政协常委会工作报告决议](https://www.gov.cn/zhuanti/2026nztj/2026qglh/yw/202603/content_7061977.htm) \\| [通过了提案工作情况报告决议](https://www.gov.cn/zhuanti/2026nztj/2026qglh/yw/202603/content_7061978.htm) \\| [通过了提案审查情况报告](https://www.gov.cn/zhuanti/2026nztj/2026qglh/yw/202603/content_7061979.htm) \\| [通过了政协第十四届全国委员会第四次会议政治决议](https://www.gov.cn/zhuanti/2026nztj/2026qglh/yw/202603/content_7061980.htm)\n\n[更多 >>](https://www.gov.cn/toutiao/)\n\n[更多>>](https://www.gov.cn/toutiao/)\n\n[![](https://www.gov.cn/shouye/datu/202603/W020260311406849603957_ORIGIN.jpg)](https://www.gov.cn/yaowen/liebiao/202603/content_7061987.htm)\n\n#### [全国政协十四届四次会议在北京闭幕](https://www.gov.cn/yaowen/liebiao/202603/content_7061987.htm)\n\n[![](https://www.gov.cn/shouye/datu/202603/W020260307734908946842_ORIGIN.jpg)](https://www.gov.cn/yaowen/liebiao/202603/content_7061462.htm)\n\n#### [习近平出席解放军和武警部队代表团全体会议](https://www.gov.cn/yaowen/liebiao/202603/content_7061462.htm)\n\n[![](https://www.gov.cn/shouye/datu/202603/W020260304821778166016_ORIGIN.jpg)](https://www.gov.cn/zhuanti/2026qglh/2026xjpdlhsj/index.htm)\n\n#### [习近平的两会时间](https://www.gov.cn/zhuanti/2026qglh/2026xjpdlhsj/index.htm)\n\n[播放](https://www.gov.cn/# \"播放\") [暂停](https://www.gov.cn/# \"暂停\")\n\n- [全国政协十四届四次会议在北京闭幕](https://www.gov.cn/#)\n- [习近平出席解放军和武警部队代表团全体会议](https://www.gov.cn/#)\n- [习近平的两会时间](https://www.gov.cn/#)\n\n## [要闻](https://www.gov.cn/yaowen/liebiao/)\n\n- [十四届全国人大四次会议举行第二次全体会议 习近平等出席](https://www.gov.cn/yaowen/liebiao/202603/content_7061810.htm)\n\n- [李强赵乐际王沪宁蔡奇丁薛祥李希分别参加全国两会一些团组审议和讨论](https://www.gov.cn/yaowen/liebiao/202603/content_7061235.htm)\n\n- [张国清将出席第二届核能峰会](https://www.gov.cn/yaowen/liebiao/202603/content_7061793.htm)\n\n- [第二场“部长通道”：回应关切真抓实干](https://www.gov.cn/zhuanti/2026nztj/2026qglh/yw/202603/content_7061863.htm)\n\n- [听民意汇民智 务实笃行开新局](https://www.gov.cn/yaowen/liebiao/202603/content_7061927.htm)\n\n- [前2个月我国进出口增速达18.3%](https://www.gov.cn/lianbo/202603/content_7061912.htm)\n\n\n![](https://www.gov.cn/images/gtrs_index_dxdcyj.jpg)\n\n### [建言征集](https://www.gov.cn/hudong/wsdy/) \\| [回应关切](https://www.gov.cn/hudong/hygq/lyhf/)\n\n[![](https://www.gov.cn/shouye/jyzjhygq/202512/W020260105796880213033_ORIGIN.jpg)](https://liuyan.www.gov.cn/2026wwzfgzbgtjy/index.htm)\n\n- [【征集中】2026“@国务院 我为政府工作报告提建议”](https://liuyan.www.gov.cn/2026wwzfgzbgtjy/index.htm)\n- [网民希望优化高速服务区充电服务，推进村镇充电桩建设，国家能源局电力司回应了](https://www.gov.cn/hudong/202511/content_7049856.htm)\n\n[![](https://www.gov.cn/images/gwyhlwdc20250623.png)](https://tousu.www.gov.cn/dc/index.htm)\n\n[我要留言](https://tousu.www.gov.cn/dc/index.htm)\n\n## [![](https://www.gov.cn/images/gtrs_index_gwywls.png)](https://www.gov.cn/gwywls/)\n\n施政为民激发活力政府建设\n\n[**以人民为中心**\\\\\n\\\\\n欢迎你@国务院。你对就业、收入、教育、医疗、住房、生态环境等有什么感受？你对完善政策措施、改进政府工作有何高招与高见？政府工作离不开大家的真知灼见。你的留言可能被转给有关部门和地方，并可能以不同形式公开。你对美好生活的向往，我们努力的方向。\\\\\n\\\\\n\\\\\n大兴调查研究之风，汲取各方智慧，辅助政府科学决策，感谢你的参与。](https://liuyan.www.gov.cn/hudong/atwls/rmqz.htm)\n\n[人民群众留言入口](https://liuyan.www.gov.cn/hudong/atwls/rmqz.htm)\n\n## [为民服务](https://www.gov.cn/fuwu/gongmin/) [更多 >>](https://www.gov.cn/fuwu/gongmin/)\n\n- [![](https://www.gov.cn/images/20240607chusheng.png)出生](https://www.gov.cn/fuwu/gongmin/chusheng/#1)\n- [![](https://www.gov.cn/images/t1_2.png)入学](https://www.gov.cn/fuwu/gongmin/ruxue/#2)\n- [![](https://www.gov.cn/images/t1_3.png)工作](https://www.gov.cn/fuwu/gongmin/gongzuo/#3)\n- [![](https://www.gov.cn/images/20240913jiuyi.png)就医](https://www.gov.cn/fu"
  },
  {
    "url": "https://www.secrss.com/articles/63000",
    "title": "404 Not Found.",
    "content": "![](https://www.secrss.com/404.png)"
  },
  {
    "url": "https://www.thepaper.cn/newsDetail_forward_26153851",
    "title": "澎湃新闻",
    "content": "[![澎湃Logo](https://www.thepaper.cn/_next/static/media/logo_light.4da59bed.png)](https://www.thepaper.cn/)\n\n- [_要闻_](https://www.thepaper.cn/)\n- [_深度_](https://www.thepaper.cn/channel_143064)\n- [_直播_](https://www.thepaper.cn/channel_128409)\n- [_视频_](https://www.thepaper.cn/channel_26916)\n- [_时事_](https://www.thepaper.cn/channel_25950)\n- [_国际_](https://www.thepaper.cn/channel_122908)\n- [_财经_](https://www.thepaper.cn/channel_25951)\n- [_视听_](https://www.thepaper.cn/channel_154646)\n- [_科技_](https://www.thepaper.cn/channel_119908)\n- [_暖闻_](https://www.thepaper.cn/channel_136261)\n- [_澎湃号_](https://www.thepaper.cn/channel_36079)\n- [_智库_](https://www.thepaper.cn/channel_119489)\n- [_思想_](https://www.thepaper.cn/channel_25952)\n- [_生活_](https://www.thepaper.cn/channel_25953)\n- [_问吧_](https://www.thepaper.cn/ask_index)\n- [_上海_](https://www.thepaper.cn/region)\n- [_奔流_](https://www.thepaper.cn/newsDetail_forward_26153851)\n- [_健康_](https://www.thepaper.cn/channel_143065)\n- [_体育_](https://www.thepaper.cn/channel_-21)\n- [_评论_](https://www.thepaper.cn/channel_-24)\n- [_ESG_](https://www.thepaper.cn/channel_122153)\n- [_文旅_](https://www.thepaper.cn/channel_143013)\n- [_短剧_](https://www.thepaper.cn/channel_150010)\n- [_关注_](https://www.thepaper.cn/follow)\n- _更多_\n\n**下载客户端**\n\n登录\n\n无障碍\n\n![](https://www.thepaper.cn/static/nomore.png)\n\n内容不存在\n\n去首页逛逛>"
  },
  {
    "url": "https://36kr.com/p/2616268291463424",
    "title": "36氪_让一部分人先看到未来",
    "content": "[账号设置](https://36kr.com/usercenter/account-password \"账号设置\") [我的关注](https://36kr.com/usercenter/follow \"我的关注\") [我的收藏](https://36kr.com/usercenter/favorite \"我的收藏\") [申请的报道](https://36kr.com/seek-report-new?tabKey=2 \"申请的报道\")退出登录\n\n登录\n\n搜索\n\n- [36氪Auto](https://img.36krcdn.com/hsossms/20230605/v2_384be8e4c1e942a28cf13a2e427fe211@18900718_oswg78404oswg320oswg320_img_png)\n\n\n\n[数字时氪](https://img.36krcdn.com/hsossms/20230605/v2_636063907bdc44389b46e7db9c761a38@18900718_oswg62424oswg320oswg320_img_png)\n\n\n\n[未来消费](https://img.36krcdn.com/hsossms/20230210/v2_38d1cdabc8404b00806de58cbedb3b7b_oswg27031oswg320oswg320_img_png)\n\n\n\n[智能涌现](https://img.36krcdn.com/hsossms/20230605/v2_da74c43ba887426f8fbccaede691b844@18900718_oswg76573oswg320oswg320_img_png)\n\n\n\n[未来城市](https://img.36krcdn.com/hsossms/20230209/v2_8c2233c88a854c6496ff4f7842a9f9dd_oswg17629oswg320oswg320_img_png)\n\n\n\n[启动Power on](https://img.36krcdn.com/hsossms/20230605/v2_632f36f1c5904a539a1e57efe4497e3a@18900718_oswg63630oswg320oswg320_img_png)\n\n\n\n[36氪出海](http://letschuhai.com/)\n\n\n\n[36氪研究院](https://img.36krcdn.com/hsossms/20230605/v2_89fa42090fae495ca5e45ba921ee42ff@18900718_oswg65306oswg320oswg320_img_png)\n\n\n\n[潮生TIDE](https://img.36krcdn.com/hsossms/20231204/v2_3b8447ffdda24a38a30fd839fd934baa@000000_oswg40121oswg430oswg430_img_jpeg)\n\n\n\n[36氪企服点评](https://img.36krcdn.com/hsossms/20230605/v2_c4720503500642d294b5be04064ef870@18900718_oswg58529oswg320oswg320_img_png)\n\n\n\n[36氪财经](https://img.36krcdn.com/hsossms/20230209/v2_d6d3f8b57fa04507915c48adf0f9620d_oswg16586oswg320oswg320_img_png)\n\n\n\n[职场bonus](https://img.36krcdn.com/hsossms/20230605/v2_efc94b0cce7043dbac883c1dfe00c810@18900718_oswg57046oswg320oswg320_img_png)\n\n\n\n[36碳](https://img.36krcdn.com/hsossms/20230209/v2_9eb02027be264174b61b9d49c391ca75_oswg15571oswg320oswg320_img_png)\n\n\n\n[后浪研究所](https://img.36krcdn.com/hsossms/20230605/v2_86f220b69e164751946d583b5472c857@18900718_oswg97988oswg320oswg320_img_png)\n\n\n\n[暗涌Waves](https://img.36krcdn.com/hsossms/20230209/v2_0c6a697748b54beea356d6e1f1fcec5f_oswg17066oswg320oswg320_img_png)\n\n\n\n[硬氪](https://img.36krcdn.com/hsossms/20230209/v2_2f845ed16244458d8887a5526c63c6d6_oswg17346oswg320oswg320_img_png)\n\n\n\n[氪睿研究院](https://img.36krcdn.com/hsossms/20251118/v2_d5e97c1ebb974011b0117c1338a9c747@000000_oswg146520oswg1280oswg1280_img_jpg)\n\n\n\n媒体品牌\n\n- [企业号](https://q.36kr.com/)\n\n\n\n[企服点评](https://www.36dianping.com/)\n\n\n\n[36Kr研究院](https://36kr.com/academe)\n\n\n\n[36Kr创新咨询](https://innovation.36kr.com/)\n\n\n\n企业服务\n\n- [核心服务](https://www.36kr.com/p/2492318105786505)\n\n\n\n[城市之窗](https://36kr.com/policy)\n\n\n\n政府服务\n\n- [创投发布](https://topics.36kr.com/topic/1645523444931974)\n\n\n\n[LP源计划](https://36kr.com/LPlan)\n\n\n\n[VClub](https://36kr.com/VClub)\n\n\n\n[VClub投资机构库](https://36kr.com/organization/)\n\n\n\n[投资机构职位推介](https://36kr.com/topics/1620276089894403)\n\n\n\n[投资人认证](https://pitchhub.36kr.com/audit-investor)\n\n\n\n投资人服务\n\n- [寻求报道](https://36kr.com/seek-report-new)\n\n\n\n[36氪Pro](https://img.36krcdn.com/hsossms/20230209/v2_95565530d4d94dc4ad904f3131c7b690_oswg23055oswg320oswg320_img_png)\n\n\n\n[创投氪堂](https://topics.36kr.com/topic/1961250130199045)\n\n\n\n[企业入驻](https://36kr.com/project-form/settled)\n\n\n\n创业者服务\n\n- 创投平台\n\n- AI测评网\n\n\n- [首页](https://36kr.com/)\n\n- [快讯](https://36kr.com/newsflashes/)\n\n- [资讯](https://36kr.com/information/web_news/)\n\n\n\n  - [推荐](https://36kr.com/information/web_recommend/)\n  - [财经](https://36kr.com/information/ccs/)\n  - [AI](https://36kr.com/information/AI/)\n  - [自助报道](https://36kr.com/information/aireport/)\n  - 城市\n\n  - [最新](https://36kr.com/information/web_news/latest/)\n  - [创投](https://36kr.com/information/contact/)\n  - [汽车](https://36kr.com/information/travel/)\n  - [科技](https://36kr.com/information/technology/)\n  - [专精特新](https://36kr.com/information/shuzihua/)\n\n- [直播](https://36kr.com/live/channel)\n\n- [视频](https://36kr.com/video/)\n\n- [专题](https://36kr.com/topics/)\n\n- [活动](https://36kr.com/activity)\n\n\n[广东](https://36kr.com/local/guangdong)\n[江苏](https://36kr.com/local/jiangsu)\n[四川](https://36kr.com/local/sichuan)\n[河南](https://36kr."
  },
  {
    "url": "https://www.infoq.cn/article/privacy-computing-2024-trends",
    "title": "InfoQ - 促进软件开发及相关领域知识与创新的传播-极客邦",
    "content": "- 企业动态\n- 行业深度\n- AI&大模型\n- 出海\n- 后端\n- 芯片&算力\n- 架构\n- 大数据\n- 软件工程\n- 云计算\n- 大前端\n- 管理/文化\n\n![404](https://static001.geekbang.org/static/infoq/www/img/404.ca54b9df.png)\n\n很抱歉，您访问的页面不存在\n\n3 秒后返回首页"
  },
  {
    "url": "https://www.alibabacloud.com/zh/knowledge/what-is-federated-learning",
    "title": "not found",
    "content": "```\n\n```\n\n![](https://img.alicdn.com/tps/TB1al7bLVXXXXXCXpXXXXXXXXXX-500-325.png_.webp)\n\n## 404! Not Found!\n\nSorry, you’ve landed on an unexplored planet!\n\n[Return Home](https://www.alibabacloud.com/)\n\nWhy Alibaba Cloud\n\n[About Alibaba Cloud](https://www.alibabacloud.com/about)\n\n[Asia Accelerator](https://www.alibabacloud.com/china-gateway)\n\n[Our Global Network](https://www.alibabacloud.com/global-locations)\n\n[Global Offices](https://www.alibabacloud.com/global-offices)\n\n[Trust Center](https://www.alibabacloud.com/trust-center)\n\n[Case Studies](https://www.alibabacloud.com/customers)\n\n[Analyst Reports](https://www.alibabacloud.com/about/analyst-reports)\n\nProducts & Pricings\n\n[Pricing Calculator](https://www.alibabacloud.com/pricing-calculator)\n\n[ECS](https://www.alibabacloud.com/product/ecs)\n\n[SAS](https://www.alibabacloud.com/product/swas)\n\n[Model Studio](https://www.alibabacloud.com/product/modelstudio)\n\n[Database](https://www.alibabacloud.com/product/databases)\n\n[Security](https://www.alibabacloud.com/product/security)\n\n[SMS](https://www.alibabacloud.com/product/short-message-service)\n\nSolutions\n\n[Financial Services](https://www.alibabacloud.com/solutions/financial/index)\n\n[Retail Services](https://www.alibabacloud.com/solutions/retail)\n\n[Media Services](https://www.alibabacloud.com/solutions/multimedia)\n\n[Gaming Services](https://www.alibabacloud.com/solutions/gaming)\n\n[ISV Solutions](https://www.alibabacloud.com/solutions/isv)\n\nEngage\n\n[Developer Community](https://www.alibabacloud.com/developer)\n\n[Partner Network](https://www.alibabacloud.com/partner/partner_network)\n\n[Startups](https://www.alibabacloud.com/startup)\n\n[Marketplace](https://marketplace.alibabacloud.com/)\n\n[Join Alibaba Cloud](https://careers.aliyun.com/home)\n\nResources & Support\n\n[Developer Learning Hub](https://www.alibabacloud.com/developer)\n\n[Documentation Center](https://www.alibabacloud.com/help)\n\n[Training & Certification](https://edu.alibabacloud.com/)\n\n[Service Notices](https://www.alibabacloud.com/notice/intl/list)\n\n[Submit a Ticket](https://smartservice.console.alibabacloud.com/service/create-ticket-intl?activeTab=1)\n\n[Security Report](https://report.alibabacloud.com/#/reportCenter/home)\n\n[Careers](https://careers.aliyun.com/en/home) [About Us](https://www.alibabacloud.com/about) [Privacy Policy](https://www.alibabacloud.com/help/faq-detail/42425.htm) [Legal](https://www.alibabacloud.com/help/en/legal) [Integrity Compliance Reporting Channel](https://aliyun.jubao.alibaba.com/) [Service Notices](https://www.alibabacloud.com/notice/intl/list) [Links](https://www.alibabacloud.com/links.html)\n\n© 2009-2026 Copyright by Alibaba Cloud All rights reserved\n\n- [Facebook](https://www.alibabacloud.com/security-notice-kfxbqr?forward=https://www.facebook.com/alibabacloud/ \"Facebook\")\n- [Linkedin](https://www.alibabacloud.com/security-notice-kfxbqr?forward=https://www.linkedin.com/company/alibabacloudtech \"Linkedin\")\n- [Twitter](https://www.alibabacloud.com/security-notice-kfxbqr?forward=https://www.twitter.com/alibaba_cloud \"Twitter\")\n- [YouTube](https://www.alibabacloud.com/security-notice-kfxbqr?forward=https://www.youtube.com/channel/UCipPA-ZHX6UYGH_Iyti1-Jw \"YouTube\")\n- [TikTok](https://www.alibabacloud.com/security-notice-kfxbqr?forward=https://www.tiktok.com/@alibaba__cloud?lang=zh-Hant-TW \"TikTok\")\n- [contact.us@alibabacloud.com](https://www.alibabacloud.com/contact-sales \"contact.us@alibabacloud.com\")\n- [Call Us Now](https://www.alibabacloud.com/contact-sales \"Call Us Now\")\n- [Discord](https://www.alibabacloud.com/security-notice-kfxbqr?forward=https://discord.com/invite/xEuwmj6qaA \"Discord\")\n\n[![TRUSTe](https://privacy-policy.truste.com/privacy-seal/seal?rid=e83a96cf-eaa2-4c82-8d85-883196fcb42c)](https://privacy.truste.com/privacy-seal/validation?rid=e83a96cf-eaa2-4c82-8d85-883196fcb42c)\n\n[![TRUSTe](https://privacy-policy.truste.com/privacy-seal/seal?rid=51be162a-c152-402b-84d2-d0a724de679a)](https://privacy.truste.com/privacy-seal/validation?rid=51be1"
  },
  {
    "url": "https://zhuanlan.zhihu.com/p/667338892",
    "title": "安全验证 - 知乎",
    "content": "![](https://www.zhihu.com/account/unhuman?type=U4E3Z1&need_login=true&session=413178463e0ae3958452a472ccd1a432&next=%2Fsignin)\n\n[知乎](https://www.zhihu.com/)\n\n请您登录后查看更多专业优质内容。\n\n_想来知乎工作？请发送邮件到 jobs@zhihu.com_"
  },
  {
    "url": "https://www.solidot.org/story?sid=80114",
    "title": "奇客Solidot | 马来西亚批准重新搜寻 MH370",
    "content": "[奇客Solidot 奇客的知识，重要的东西](https://www.solidot.org/ \"奇客Solidot 奇客的知识，重要的东西\")\n\n[登录](https://www.solidot.org/login) [注册](https://www.solidot.org/register)\n\n- 文章\n[往日文章](https://www.solidot.org/?issue=20260310) [往日投票](https://www.solidot.org/polllist)\n\n- 皮肤\n[蓝色](https://www.solidot.org/?theme=blue) [橙色](https://www.solidot.org/?theme=yellow) [绿色](https://www.solidot.org/?theme=green) [浅绿色](https://www.solidot.org/?theme=clightgreen)\n\n\n## 关注我们：\n\n- [rss](https://www.solidot.org/index.rss \"rss\")\n- [喜马拉雅](http://www.ximalaya.com/keji/16007374/ \"喜马拉雅\")\n\nsolidot新版网站常见问题，请点击 [这里](https://www.solidot.org/QA) 查看。\n\n## 消息\n\n**本文已被查看 4800 次**\n\n## 马来西亚批准重新搜寻 MH370\n\n[![新闻](https://icon.solidot.org/images/topics/topicnews.png?123)](https://www.solidot.org/search?tid=6 \"新闻\")\n\n[Wilson](https://www.solidot.org/~Wilson) (42865)发表于 2024年12月20日 23时36分 星期五\n\n\n![](https://icon.solidot.org/images/a7c7.png)\n\n**来自夜焰**\n\n马来西亚批准重新搜寻失踪逾十年的 MH370。从吉隆坡飞往北京的 MH370 航班于 2014 年 3 月 8 日失踪，当时机上有 239 人。马来西亚交通部长 Anthony Loke 周五表示，内阁原则上批准了与美国海洋勘探公司 Ocean Infinity 达成的 $70m 搜寻交易。根据“无发现不收费”方案，Ocean Infinity 只有在找到飞机残骸后才能获得报酬。Ocean Infinity 在 2018 年曾达成类似协议，但三个月搜寻一无所获。Loke 表示达成的协议是原则性的，具体条款还需要等到明年初才能敲定。最新的搜寻针对的是南印度洋一块 15,000 平方公里的区域。\n\nhttps://www.bbc.com/news/articles/cewxnwe5d11o\n\n[天文学家发现某种星际间“高速公路”](https://www.solidot.org/story?sid=80113)\n\n[德国主权科技基金投资 OpenStreetMap 项目](https://www.solidot.org/story?sid=80115)\n\n﻿"
  }
]